h5json/__init__.py
h5json/hdf5db.py
h5json/hdf5dtype.py
h5json/jsontoh5.py
h5json-1.0.2.data/scripts/h5tojson.py
h5json-1.0.2.data/scripts/jsontoh5.py
h5json-1.0.2.dist-info/DESCRIPTION.rst
h5json-1.0.2.dist-info/METADATA
h5json-1.0.2.dist-info/RECORD
h5json-1.0.2.dist-info/WHEEL
h5json-1.0.2.dist-info/metadata.json
h5json-1.0.2.dist-info/pbr.json
h5json-1.0.2.dist-info/top_level.txt
h5tojson/__init__.py
h5tojson/h5tojson.py
jsontoh5/__init__.py
jsontoh5/jsontoh5.py
test/integ/__init__.py
test/integ/h5tojson_test.py
test/integ/jsontoh5_test.py
test/unit/__init__.py
test/unit/hdf5dbTest.py
test/unit/hdf5dtypeTest.py
