Metadata-Version: 2.0
Name: h5json
Version: 1.0.2
Summary: A sample Python project
Home-page: https://github.com/HDFGroup/hdf5-json
Author: John Readey
Author-email: jreadey@hdfgroup.org
License: BSD
Keywords: json hdf5 numpy array data
Platform: UNKNOWN
Classifier: Development Status :: 5 - Production/Stable
Classifier: Intended Audience :: Developers
Classifier: Topic :: Software Development :: Build Tools
Classifier: License :: OSI Approved :: BSD License
Classifier: Programming Language :: Python :: 2
Classifier: Programming Language :: Python :: 2.7
Classifier: Programming Language :: Python :: 3
Classifier: Programming Language :: Python :: 3.2
Classifier: Programming Language :: Python :: 3.3
Classifier: Programming Language :: Python :: 3.4
Classifier: Programming Language :: Python :: 3.5
Requires-Dist: h5py (>=2.5)
Requires-Dist: numpy (>=1.6.1)
Provides-Extra: dev
Requires-Dist: check-manifest; extra == 'dev'
Provides-Extra: test
Requires-Dist: coverage; extra == 'test'
